{
    "sections": [
        {
            "component": "About",
            "path": "/about",
            "headerTitle": "Обо мне"
        },
        {
            "component": "Skills",
            "path": "/skills",
            "headerTitle": "Навыки"
        },
        {
            "component": "Education",
            "path": "/education",
            "headerTitle": "Обучение"
        },
        {
            "component": "Experience",
            "path": "/experience",
            "headerTitle": "Опыт"
        },
        {
            "component": "Projects",
            "path": "/projects",
            "headerTitle": "Проекты"
        }
    ]
}